README.md
setup.py
examples/e1.json
noliboskar/__init__.py
noliboskar/me.py
noliboskar.egg-info/PKG-INFO
noliboskar.egg-info/SOURCES.txt
noliboskar.egg-info/dependency_links.txt
noliboskar.egg-info/top_level.txt