Metadata-Version: 2.1
Name: noliboskar
Version: 0.0.4
Summary: My test package
Home-page: UNKNOWN
Author: Oskar
Author-email: example@example.com
License: MIT
Platform: UNKNOWN
